python_middlewareable/__init__.py
python_middlewareable/middleware.py
python_middlewareable/middlewareable.py
python_middlewareable/request.py
python_middlewareable/traits/auto_instantiable/auto_instantiable.py
python_middlewareable/traits/data_structurable/data_structurable.py
python_middlewareable/traits/data_structurable/dtos/request_data.py
python_middlewareable/traits/data_structurable/dtos/response_data.py
python_middlewareable/traits/data_structurable/dtos/transport_data.py
python_middlewareable/traits/data_structurable/mixins/request_mixin.py
python_middlewareable-1.0.0.dist-info/LICENSE
python_middlewareable-1.0.0.dist-info/METADATA
python_middlewareable-1.0.0.dist-info/WHEEL
python_middlewareable-1.0.0.dist-info/top_level.txt
python_middlewareable-1.0.0.dist-info/RECORD
