Metadata-Version: 2.1
Name: python-middlewareable
Version: 1.0.0
Summary: A simple library for working with middlewares in Python
Author-email: TheCodeCrate <loureiro.rg@gmail.com>
License: The MIT License (MIT)
Project-URL: repository, https://github.com/thecodecrate/python-middlewareable
Project-URL: documentation, https://github.com/thecodecrate/python-middlewareable
Keywords: middleware,python,library,request-handling,python-middleware
Classifier: License :: OSI Approved :: MIT License
Classifier: Programming Language :: Python
Classifier: Programming Language :: Python :: 3
Classifier: Programming Language :: Python :: 3.7
Classifier: Programming Language :: Python :: 3.8
Classifier: Programming Language :: Python :: 3.9
Classifier: Programming Language :: Python :: 3.10
Classifier: Programming Language :: Python :: 3.11
Classifier: Intended Audience :: Developers
Classifier: Topic :: Software Development :: Libraries :: Python Modules
Classifier: Typing :: Typed
Requires-Python: >=3.7
License-File: LICENSE
Provides-Extra: build
Requires-Dist: build; extra == "build"
Requires-Dist: twine; extra == "build"
Provides-Extra: dev
Requires-Dist: black; extra == "dev"
Requires-Dist: bumpver; extra == "dev"
Requires-Dist: isort; extra == "dev"
Requires-Dist: flake8; extra == "dev"
Requires-Dist: pytest; extra == "dev"
